y_py-0.6.2.dist-info/METADATA
y_py-0.6.2.dist-info/WHEEL
y_py-0.6.2.dist-info/license_files/LICENSE
y_py/__init__.py
y_py/__init__.pyi
y_py/py.typed
y_py/y_py.cpython-311-x86_64-linux-gnu.so
y_py-0.6.2.dist-info/RECORD
