Metadata-Version: 2.1
Name: y-py
Version: 0.6.2
Classifier: Development Status :: 4 - Beta
Classifier: Intended Audience :: Developers
Classifier: License :: OSI Approved :: MIT License
Classifier: Programming Language :: Python
Classifier: Programming Language :: Python :: 3.7
Classifier: Programming Language :: Python :: 3.8
Classifier: Programming Language :: Python :: 3.9
Classifier: Programming Language :: Python :: 3.10
Classifier: Programming Language :: Python :: 3.11
Classifier: Programming Language :: Python :: 3.12
Classifier: Programming Language :: Rust
License-File: LICENSE
Summary: Python bindings for the Y-CRDT built from yrs (Rust)
Keywords: crdt
Author-email: John Waidhofer <waidhoferj@gmail.com>, Kevin Jahns <kevin.jahns@protonmail.com>, Pierre-Olivier Simonard <pierre.olivier.simonard@gmail.com>
Project-URL: Homepage, https://github.com/y-crdt/ypy
Project-URL: Source, https://github.com/y-crdt/ypy
Project-URL: Issues, https://github.com/y-crdt/ypy/issues
Project-URL: Pypi, https://pypi.org/project/y-py
